{
  "appInfo" : {
    "build" : "212.5712.43.2112.8609683",
    "buildDate" : "2022-05-18T16:50:00.77Z[UTC]",
    "productCode" : "AI",
    "generated" : "2022-07-07T09:10:44.613606Z",
    "os" : "Windows 10 10.0",
    "runtime" : "JetBrains s.r.o 11.0.12 11.0.12+7-b1504.28-7817840"
  },
  "runtimeInfo" : {
    "maxMemory" : 1342177280,
    "numberOfProcessors" : 12,
    "maxNumberOfIndexingThreads" : 4,
    "maxSizeOfFileForIntelliSense" : 2560000,
    "maxSizeOfFileForContentLoading" : 20971520
  },
  "projectIndexingHistory" : {
    "projectName" : "Weather App",
    "times" : {
      "indexingReason" : "On refresh of 17 files",
      "totalUpdatingTime" : 192067400,
      "indexingTime" : 177651700,
      "contentLoadingTime" : 3925494,
      "scanFilesTime" : 2770500,
      "pushPropertiesTime" : 0,
      "indexExtensionsTime" : 0,
      "updatingStart" : "2022-07-07T09:10:44.4131132Z",
      "updatingEnd" : "2022-07-07T09:10:44.6047637Z",
      "totalSuspendedTime" : 0,
      "wasInterrupted" : false
    },
    "fileCount" : {
      "numberOfFileProviders" : 1,
      "numberOfScannedFiles" : 17,
      "numberOfFilesIndexedByInfrastructureExtensionsDuringScan" : 0,
      "numberOfFilesScheduledForIndexingAfterScan" : 17,
      "numberOfFilesIndexedByInfrastructureExtensionsDuringIndexingStage" : 0,
      "numberOfFilesIndexedWithLoadingContent" : 17
    },
    "totalStatsPerFileType" : [ {
      "fileType" : "textmate",
      "partOfTotalProcessingTime" : {
        "part" : 212772800,
        "total" : 237378200
      },
      "partOfTotalContentLoadingTime" : {
        "part" : 3491000,
        "total" : 5233900
      },
      "totalNumberOfFiles" : 4,
      "totalFilesSize" : 3033176,
      "indexingSpeed" : {
        "totalBytes" : 3033176,
        "totalTime" : 212772800
      },
      "biggestContributors" : [ {
        "providerName" : "Refreshed files",
        "numberOfFiles" : 4,
        "totalFilesSize" : 3033176,
        "partOfTotalProcessingTimeOfThisFileType" : {
          "part" : 212772800,
          "total" : 212772800
        }
      } ]
    }, {
      "fileType" : "PLAIN_TEXT",
      "partOfTotalProcessingTime" : {
        "part" : 19867500,
        "total" : 237378200
      },
      "partOfTotalContentLoadingTime" : {
        "part" : 810000,
        "total" : 5233900
      },
      "totalNumberOfFiles" : 3,
      "totalFilesSize" : 229530,
      "indexingSpeed" : {
        "totalBytes" : 229530,
        "totalTime" : 19867500
      },
      "biggestContributors" : [ {
        "providerName" : "Refreshed files",
        "numberOfFiles" : 3,
        "totalFilesSize" : 229530,
        "partOfTotalProcessingTimeOfThisFileType" : {
          "part" : 19867500,
          "total" : 19867500
        }
      } ]
    }, {
      "fileType" : "HTML",
      "partOfTotalProcessingTime" : {
        "part" : 4106900,
        "total" : 237378200
      },
      "partOfTotalContentLoadingTime" : {
        "part" : 619300,
        "total" : 5233900
      },
      "totalNumberOfFiles" : 3,
      "totalFilesSize" : 33234,
      "indexingSpeed" : {
        "totalBytes" : 33234,
        "totalTime" : 4106900
      },
      "biggestContributors" : [ {
        "providerName" : "Refreshed files",
        "numberOfFiles" : 3,
        "totalFilesSize" : 33234,
        "partOfTotalProcessingTimeOfThisFileType" : {
          "part" : 4106900,
          "total" : 4106900
        }
      } ]
    }, {
      "fileType" : "JSON",
      "partOfTotalProcessingTime" : {
        "part" : 385000,
        "total" : 237378200
      },
      "partOfTotalContentLoadingTime" : {
        "part" : 263100,
        "total" : 5233900
      },
      "totalNumberOfFiles" : 2,
      "totalFilesSize" : 15542,
      "indexingSpeed" : {
        "totalBytes" : 15542,
        "totalTime" : 385000
      },
      "biggestContributors" : [ {
        "providerName" : "Refreshed files",
        "numberOfFiles" : 2,
        "totalFilesSize" : 15542,
        "partOfTotalProcessingTimeOfThisFileType" : {
          "part" : 385000,
          "total" : 385000
        }
      } ]
    }, {
      "fileType" : "UNKNOWN",
      "partOfTotalProcessingTime" : {
        "part" : 246000,
        "total" : 237378200
      },
      "partOfTotalContentLoadingTime" : {
        "part" : 50500,
        "total" : 5233900
      },
      "totalNumberOfFiles" : 5,
      "totalFilesSize" : 0,
      "indexingSpeed" : {
        "totalBytes" : 0,
        "totalTime" : 246000
      },
      "biggestContributors" : [ {
        "providerName" : "Refreshed files",
        "numberOfFiles" : 5,
        "totalFilesSize" : 0,
        "partOfTotalProcessingTimeOfThisFileType" : {
          "part" : 246000,
          "total" : 246000
        }
      } ]
    } ],
    "totalStatsPerIndexer" : [ {
      "indexId" : "TodoIndex",
      "partOfTotalIndexingTime" : {
        "part" : 69952700,
        "total" : 76871400
      },
      "totalNumberOfFiles" : 2,
      "totalNumberOfFilesIndexedByExtensions" : 0,
      "totalFilesSize" : 1596338,
      "indexingSpeed" : {
        "totalBytes" : 1596338,
        "totalTime" : 69952700
      },
      "snapshotInputMappingStats" : {
        "totalRequests" : 0,
        "totalMisses" : 0,
        "totalHits" : 0
      }
    }, {
      "indexId" : "Stubs",
      "partOfTotalIndexingTime" : {
        "part" : 2891200,
        "total" : 76871400
      },
      "totalNumberOfFiles" : 1,
      "totalNumberOfFilesIndexedByExtensions" : 0,
      "totalFilesSize" : 12447,
      "indexingSpeed" : {
        "totalBytes" : 12447,
        "totalTime" : 2891200
      },
      "snapshotInputMappingStats" : {
        "totalRequests" : 0,
        "totalMisses" : 0,
        "totalHits" : 0
      }
    }, {
      "indexId" : "Trigram.Index",
      "partOfTotalIndexingTime" : {
        "part" : 2326900,
        "total" : 76871400
      },
      "totalNumberOfFiles" : 1,
      "totalNumberOfFilesIndexedByExtensions" : 0,
      "totalFilesSize" : 149049,
      "indexingSpeed" : {
        "totalBytes" : 149049,
        "totalTime" : 2326900
      },
      "snapshotInputMappingStats" : {
        "totalRequests" : 0,
        "totalMisses" : 0,
        "totalHits" : 0
      }
    }, {
      "indexId" : "IdIndex",
      "partOfTotalIndexingTime" : {
        "part" : 1700600,
        "total" : 76871400
      },
      "totalNumberOfFiles" : 1,
      "totalNumberOfFilesIndexedByExtensions" : 0,
      "totalFilesSize" : 149049,
      "indexingSpeed" : {
        "totalBytes" : 149049,
        "totalTime" : 1700600
      },
      "snapshotInputMappingStats" : {
        "totalRequests" : 0,
        "totalMisses" : 0,
        "totalHits" : 0
      }
    } ],
    "scanningStatistics" : [ {
      "providerName" : "Refreshed files",
      "numberOfScannedFiles" : 17,
      "numberOfSkippedFiles" : 0,
      "numberOfFilesForIndexing" : 17,
      "numberOfFilesFullyIndexedByInfrastructureExtensions" : 0,
      "scanningTime" : 2770500,
      "timeProcessingUpToDateFiles" : 0,
      "timeUpdatingContentLessIndexes" : 0,
      "timeIndexingWithoutContent" : 0
    } ],
    "fileProviderStatistics" : [ {
      "providerName" : "Refreshed files",
      "totalNumberOfIndexedFiles" : 17,
      "totalNumberOfFilesFullyIndexedByExtensions" : 0,
      "totalIndexingTime" : 178036800,
      "contentLoadingTime" : 3925494,
      "numberOfTooLargeForIndexingFiles" : 0,
      "slowIndexedFiles" : [ ]
    } ]
  }
}